<odoo>

    <record id="supervisor_view_tree" model="ir.ui.view">
        <field name="name">supervisor tree</field>
        <field name="model">supervisor</field>
        <field name="arch" type="xml">
            <tree>
                <field name="ref"/>
                <field name="supervisor_id"/>
                <field name="name"/>
                <field name="hire_date"/>
                <field name="phone"/>
                <field name="email"/>
                <field name="address"/>
                <field name="active" invisible="True"/>
            </tree>
        </field>
    </record>

    <record id="supervisor_view_form" model="ir.ui.view">
        <field name="name">supervisor form</field>
        <field name="model">supervisor</field>
        <field name="arch" type="xml">
            <form>
                <sheet>
                    <widget name="web_ribbon" title="Archived" bg_color="text-bg-danger" invisible="active"/>
                    <div class="oe_title">
                        <label for="ref"/>
                        <h1>
                            <field name="ref"/>
                        </h1>
                    </div>
                    <group>
                        <group string="General info">
                            <field name="active" invisible="True"/>
                            <field name="name"/>
                            <field name="supervisor_id"/>
                            <field name="hire_date"/>
                        </group>
                        <group string="Additional info">
                            <field name="phone"/>
                            <field name="email"/>
                            <field name="address" placeholder="State Locality City"/>
                        </group>
                    </group>
                </sheet>
                    <div class="oe_chatter">
                    <field name="message_follower_ids"/>
                    <field name="activity_ids"/>
                    <field name="message_ids"/>
                </div>
            </form>
        </field>
    </record>


    <record id="supervisor_view_search" model="ir.ui.view">
        <field name="name">supervisor search</field>
        <field name="model">supervisor</field>
        <field name="arch" type="xml">
            <search>
                <field name="supervisor_id"/>
            </search>
        </field>
    </record>



    <record id="supervisor_action" model="ir.actions.act_window">
        <field name="name">supervisor</field>
        <field name="res_model">supervisor</field>
    </record>




    <menuitem
            id="supervisor_menu_item"
            name="Supervisors"
            parent="partners_menu"
            action="supervisor_action"
    />
</odoo>